Workbook

Sheet Test Scenarios
A1: Test Scenario ID | B1: Reference | C1: Test Scenario Description | D1: Priority | E1: Number of Test Cases
A2: TS_001 | B2: FRS | C2: Register Functionality | D2: P0 | E2: 27
A3: TS_002 | B3: FRS | C3: Login Functionality | D3: P0 | E3: 23
A4: TS_003 | B4: FRS | C4: Logout Functionality | D4: P0 | E4: 11
A5: TS_004 | B5: FRS | C5: Forgot Password | D5: P2 | E5: 25
A6: TS_005 | B6: FRS | C6: Search Functionality | D6: P1 | E6: 22
A7: TS_006 | B7: FRS | C7: Product Compare | D7: P4 | E7: 24
A8: TS_007 | B8: FRS | C8: Product Display Page | D8: P1 | E8: 37
A9: TS_008 | B9: FRS | C9: Add to Cart | D9: P1 | E9: 9
A10: TS_009 | B10: FRS | C10: Wish List | D10: P4 | E10: 21
A11: TS_010 | B11: FRS | C11: Shopping Cart | D11: P1 | E11: 33
A12: TS_011 | B12: FRS | C12: Home Page | D12: P2 | E12: 10
A13: TS_012 | B13: FRS | C13: Checkout | D13: P1 | E13: 20
A14: TS_013 | B14: FRS | C14: My Account | D14: P2 | E14: 9
C15: TOTAL TEST CASES | E15: =SUM(E2:E14) -> 271

Sheet Test Cases
A1: Test Case ID | B1: Test Scenario ID | C1: Reference | D1: Module | E1: Test Case Title | F1: Preconditions | G1: Test Steps | H1: Test Data | I1: Expected Result | J1: Priority | K1: Test Type | L1: Status | M1: Actual Result | N1: Defect ID | O1: Executed By | P1: Execution Date
A2: TC_0001 | B2: TS_001 | C2: FRS | D2: Register | E2: Register with valid mandatory data | F2: User is on the Registration page and is not logged in. | G2: 1. Navigate to the Registration page. 2. Enter a valid first name, last name, and a unique email address. 3. Enter a password that meets complexity rules. 4. Re-enter the same password in the Confirm Password field. 5. Check the 'I agree to Terms and Conditions' checkbox. 6. Click the Register button. | H2: First Name: Sarah | Last Name: Ahmed | Email: sarah.ahmed01@example.com | Password: Passw0rd!23 | I2: Account is created successfully, a confirmation message is shown, and the user is redirected to the login page or homepage as a logged-in user. | J2: P0 | K2: Positive | L2: Pass | M2: Account created successfully; redirected to homepage as logged-in user. | O2: Ali Hassan | P2: 2026-09-15
A3: TC_0002 | B3: TS_001 | C3: FRS | D3: Register | E3: Register with empty First Name field | F3: User is on the Registration page. | G3: 1. Leave the First Name field empty. 2. Fill in all other required fields with valid data. 3. Click the Register button. | H3: First Name: (empty) | Last Name: Hassan | Email: hassan.t@example.com | Password: Passw0rd!23 | I3: Registration is blocked and an inline validation message 'First name is required' is displayed under the First Name field. | J3: P0 | K3: Negative - Required Field Validation | L3: Pass | M3: Validation message 'First name is required' displayed as expected. | O3: Mona Fathy | P3: 2026-09-15
A4: TC_0003 | B4: TS_001 | C4: FRS | D4: Register | E4: Register with empty Last Name field | F4: User is on the Registration page. | G4: 1. Leave the Last Name field empty. 2. Fill in all other required fields with valid data. 3. Click the Register button. | H4: First Name: Omar | Last Name: (empty) | Email: omar.k@example.com | Password: Passw0rd!23 | I4: Registration is blocked and an inline validation message 'Last name is required' is displayed under the Last Name field. | J4: P0 | K4: Negative - Required Field Validation | L4: Pass
A5: TC_0004 | B5: TS_001 | C5: FRS | D5: Register | E5: Register with empty Email field | F5: User is on the Registration page. | G5: 1. Leave the Email field empty. 2. Fill in all other required fields with valid data. 3. Click the Register button. | H5: Email: (empty) | I5: Registration is blocked and an inline validation message 'Email is required' is displayed under the Email field. | J5: P0 | K5: Negative - Required Field Validation | L5: Pass
A6: TC_0005 | B6: TS_001 | C6: FRS | D6: Register | E6: Register with empty Password field | F6: User is on the Registration page. | G6: 1. Leave the Password field empty. 2. Fill in all other required fields with valid data. 3. Click the Register button. | H6: Password: (empty) | I6: Registration is blocked and an inline validation message 'Password is required' is displayed under the Password field. | J6: P0 | K6: Negative - Required Field Validation | L6: Pass
A7: TC_0006 | B7: TS_001 | C7: FRS | D7: Register | E7: Register with empty Confirm Password field | F7: User is on the Registration page. | G7: 1. Enter a valid password in the Password field. 2. Leave the Confirm Password field empty. 3. Click the Register button. | H7: Password: Passw0rd!23 | Confirm Password: (empty) | I7: Registration is blocked and a validation message 'Please confirm your password' is displayed. | J7: P0 | K7: Negative - Required Field Validation | L7: Pass
A8: TC_0007 | B8: TS_001 | C8: FRS | D8: Register | E8: Register with invalid email format - missing @ symbol | F8: User is on the Registration page. | G8: 1. Fill in all fields with valid data. 2. Enter an email address without an '@' symbol. 3. Click the Register button. | H8: Email: sarahexample.com | I8: Registration is blocked and a validation message 'Please enter a valid email address' is displayed. | J8: P0 | K8: Negative - Field Format Validation | L8: Pass
A9: TC_0008 | B9: TS_001 | C9: FRS | D9: Register | E9: Register with invalid email format - missing domain | F9: User is on the Registration page. | G9: 1. Fill in all fields with valid data. 2. Enter an email address without a domain after the '@' symbol. 3. Click the Register button. | H9: Email: sarah.ahmed@ | I9: Registration is blocked and a validation message 'Please enter a valid email address' is displayed. | J9: P0 | K9: Negative - Field Format Validation | L9: Pass
A10: TC_0009 | B10: TS_001 | C10: FRS | D10: Register | E10: Register with an already registered email address | F10: An account already exists with the email 'existing.user@example.com'. | G10: 1. Navigate to the Registration page. 2. Fill in the form using an email address that is already registered. 3. Click the Register button. | H10: Email: existing.user@example.com | I10: Registration is blocked and an error message 'An account with this email already exists' is displayed, with a suggestion to log in instead. | J10: P0 | K10: Negative - Business Rule Validation | L10: Fail | M10: Registration succeeded with a duplicate email; no error message was shown. | N10: BUG_001 | O10: Mona Fathy | P10: 2026-09-15
A11: TC_0010 | B11: TS_001 | C11: FRS | D11: Register | E11: Register with password shorter than minimum allowed length | F11: User is on the Registration page. Minimum password length is 8 characters. | G11: 1. Fill in all fields with valid data. 2. Enter a password with 7 characters. 3. Click the Register button. | H11: Password: Pas1!aB (7 characters) | I11: Registration is blocked and a validation message 'Password must be at least 8 characters long' is displayed. | J11: P0 | K11: Boundary Value Analysis | L11: Not Run
A12: TC_0011 | B12: TS_001 | C12: FRS | D12: Register | E12: Register with password at exact minimum allowed length | F12: User is on the Registration page. Minimum password length is 8 characters. | G12: 1. Fill in all fields with valid data. 2. Enter a password with exactly 8 characters meeting complexity rules. 3. Click the Register button. | H12: Password: Pass1!aB (8 characters) | I12: Password is accepted and the account is registered successfully. | J12: P0 | K12: Boundary Value Analysis | L12: Not Run
A13: TC_0012 | B13: TS_001 | C13: FRS | D13: Register | E13: Register with password exceeding maximum allowed length | F13: User is on the Registration page. Maximum password length is 20 characters. | G13: 1. Fill in all fields with valid data. 2. Enter a password with 21 characters. 3. Click the Register button. | H13: Password: Passw0rd!23456789ABCX (21 characters) | I13: Registration is blocked and a validation message 'Password must not exceed 20 characters' is displayed. | J13: P0 | K13: Boundary Value Analysis | L13: Not Run
A14: TC_0013 | B14: TS_001 | C14: FRS | D14: Register | E14: Register with password missing an uppercase letter | F14: User is on the Registration page. | G14: 1. Fill in all fields with valid data. 2. Enter a password containing only lowercase letters, numbers, and symbols. 3. Click the Register button. | H14: Password: passw0rd!23 | I14: Registration is blocked and a validation message 'Password must contain at least one uppercase letter' is displayed. | J14: P0 | K14: Validation Testing | L14: Pass | M14: Password with missing uppercase letter correctly rejected. | O14: Ali Hassan | P14: 2026-09-15
A15: TC_0014 | B15: TS_001 | C15: FRS | D15: Register | E15: Register with password missing a numeric character | F15: User is on the Registration page. | G15: 1. Fill in all fields with valid data. 2. Enter a password without any digits. 3. Click the Register button. | H15: Password: Password!ABC | I15: Registration is blocked and a validation message 'Password must contain at least one number' is displayed. | J15: P0 | K15: Validation Testing | L15: Pass
A16: TC_0015 | B16: TS_001 | C16: FRS | D16: Register | E16: Register with password missing a special character | F16: User is on the Registration page. | G16: 1. Fill in all fields with valid data. 2. Enter a password containing only letters and numbers. 3. Click the Register button. | H16: Password: Passw0rd123 | I16: Registration is blocked and a validation message 'Password must contain at least one special character' is displayed. | J16: P0 | K16: Validation Testing | L16: Pass
A17: TC_0016 | B17: TS_001 | C17: FRS | D17: Register | E17: Register with mismatched Password and Confirm Password | F17: User is on the Registration page. | G17: 1. Fill in all fields with valid data. 2. Enter a valid password in the Password field. 3. Enter a different value in the Confirm Password field. 4. Click the Register button. | H17: Password: Passw0rd!23 | Confirm Password: Passw0rd!24 | I17: Registration is blocked and a validation message 'Passwords do not match' is displayed. | J17: P0 | K17: Negative - Field Validation | L17: Pass
A18: TC_0017 | B18: TS_001 | C18: FRS | D18: Register | E18: Register with SQL injection payload in the Email field | F18: User is on the Registration page. | G18: 1. Fill in all other fields with valid data. 2. Enter a SQL injection payload in the Email field. 3. Click the Register button. | H18: Email: ' OR '1'='1'; DROP TABLE Users;-- | I18: Input is rejected by client-side/server-side validation as an invalid email; no database error is exposed and no data is compromised. | J18: P0 | K18: Security Testing | L18: Pass
A19: TC_0018 | B19: TS_001 | C19: FRS | D19: Register | E19: Register with script tag in the First Name field (XSS attempt) | F19: User is on the Registration page. | G19: 1. Fill in all other fields with valid data. 2. Enter a script tag as the First Name. 3. Click the Register button. | H19: First Name: <script>alert('xss')</script> | I19: The script is not executed and is either rejected with a validation message or safely encoded/sanitized when stored and displayed. | J19: P0 | K19: Security Testing | L19: Pass
A20: TC_0019 | B20: TS_001 | C20: FRS | D20: Register | E20: Register with leading and trailing spaces in the Email field | F20: User is on the Registration page. | G20: 1. Fill in all fields with valid data. 2. Enter an email address with leading and trailing spaces. 3. Click the Register button. | H20: Email: ' sarah.ahmed01@example.com ' | I20: The application trims the spaces automatically and registers the account successfully with the cleaned email value. | J20: P0 | K20: Equivalence Partitioning | L20: Pass
A21: TC_0020 | B21: TS_001 | C21: FRS | D21: Register | E21: Register with numeric characters in the First Name field | F21: User is on the Registration page. | G21: 1. Fill in all fields with valid data. 2. Enter numeric characters in the First Name field. 3. Click the Register button. | H21: First Name: 12345 | I21: Registration is blocked and a validation message 'First name must contain only letters' is displayed. | J21: P0 | K21: Validation Testing | L21: Pass
A22: TC_0021 | B22: TS_001 | C22: FRS | D22: Register | E22: Register with special characters in the First Name field | F22: User is on the Registration page. | G22: 1. Fill in all fields with valid data. 2. Enter special characters in the First Name field. 3. Click the Register button. | H22: First Name: @#$%^& | I22: Registration is blocked and a validation message 'First name contains invalid characters' is displayed. | J22: P0 | K22: Validation Testing | L22: Pass
A23: TC_0022 | B23: TS_001 | C23: FRS | D23: Register | E23: Register without accepting Terms and Conditions | F23: User is on the Registration page and the Terms and Conditions checkbox is unchecked by default. | G23: 1. Fill in all required fields with valid data. 2. Leave the 'I agree to Terms and Conditions' checkbox unchecked. 3. Click the Register button. | H23: All fields valid, Terms checkbox: unchecked | I23: Registration is blocked and a message 'You must accept the Terms and Conditions to continue' is displayed. | J23: P0 | K23: Business Rule Validation | L23: Pass
A24: TC_0023 | B24: TS_001 | C24: FRS | D24: Register | E24: Register with a valid phone number format | F24: User is on the Registration page and the form includes an optional/required Phone Number field. | G24: 1. Fill in all required fields with valid data. 2. Enter a valid phone number in the Phone Number field. 3. Click the Register button. | H24: Phone: +201012345678 | I24: The phone number is accepted and the account is registered successfully. | J24: P0 | K24: Positive | L24: Pass
A25: TC_0024 | B25: TS_001 | C25: FRS | D25: Register | E25: Register with an invalid phone number format | F25: User is on the Registration page. | G25: 1. Fill in all required fields with valid data. 2. Enter an invalid phone number containing letters. 3. Click the Register button. | H25: Phone: 12A-BC-4567 | I25: Registration is blocked and a validation message 'Please enter a valid phone number' is displayed. | J25: P0 | K25: Negative - Field Format Validation | L25: Pass
A26: TC_0025 | B26: TS_001 | C26: FRS | D26: Register | E26: Verify duplicate submission is prevented on double-click of Register button | F26: User is on the Registration page with all fields filled with valid data. | G26: 1. Fill in all required fields with valid, unique data. 2. Rapidly double-click the Register button before the page responds. | H26: All fields valid and unique | I26: Only one account is created; the button is disabled or shows a loading state after the first click, preventing a duplicate submission/duplicate account. | J26: P0 | K26: Negative - Regression | L26: Pass | M26: Duplicate click prevented; only one account created. | O26: Youssef Adel | P26: 2026-09-16
A27: TC_0026 | B27: TS_001 | C27: FRS | D27: Register | E27: Verify navigation from Register page to Login page | F27: User is on the Registration page. | G27: 1. Locate the 'Already have an account? Login' link. 2. Click the link. | H27: N/A | I27: The user is navigated to the Login page successfully. | J27: P0 | K27: Navigation Testing | L27: Pass
A28: TC_0027 | B28: TS_001 | C28: FRS | D28: Register | E28: Verify Password field masks entered characters | F28: User is on the Registration page. | G28: 1. Click into the Password field. 2. Type a password. 3. Observe the displayed characters. | H28: Password: Passw0rd!23 | I28: Entered characters are masked (displayed as dots/asterisks) by default to protect the password from shoulder-surfing. | J28: P0 | K28: UI Testing | L28: Pass
A29: TC_0028 | B29: TS_002 | C29: FRS | D29: Login | E29: Login with valid registered credentials | F29: User has a registered and active account. | G29: 1. Navigate to the Login page. 2. Enter a valid registered email address. 3. Enter the correct password. 4. Click the Login button. | H29: Email: testuser@example.com | Password: ValidPassword123! | I29: The user is successfully authenticated and redirected to the homepage or account dashboard. | J29: P0 | K29: Positive | L29: Pass | M29: Valid login succeeded; redirected to homepage. | O29: Mona Fathy | P29: 2026-09-16
A30: TC_0029 | B30: TS_002 | C30: FRS | D30: Login | E30: Login with an incorrect password | F30: User has a registered account. | G30: 1. Navigate to the Login page. 2. Enter a valid registered email address. 3. Enter an incorrect password. 4. Click the Login button. | H30: Email: testuser@example.com | Password: WrongPass1! | I30: Login is rejected and an error message 'Invalid email or password' is displayed; the user remains on the login page. | J30: P0 | K30: Negative | L30: Pass | M30: Invalid password correctly rejected with generic error. | O30: Mona Fathy | P30: 2026-09-16
A31: TC_0030 | B31: TS_002 | C31: FRS | D31: Login | E31: Login with an unregistered email address | F31: The email address used is not associated with any account. | G31: 1. Navigate to the Login page. 2. Enter an email address that is not registered. 3. Enter any password. 4. Click the Login button. | H31: Email: notregistered@example.com | Password: AnyPassword1! | I31: Login is rejected and a generic error message 'Invalid email or password' is displayed without revealing whether the email exists. | J31: P0 | K31: Negative | L31: Pass
A32: TC_0031 | B32: TS_002 | C32: FRS | D32: Login | E32: Login with empty Email field | F32: User is on the Login page. | G32: 1. Leave the Email field empty. 2. Enter a valid password. 3. Click the Login button. | H32: Email: (empty) | Password: ValidPassword123! | I32: Login is blocked and a validation message 'Email is required' is displayed. | J32: P0 | K32: Negative - Required Field Validation | L32: Pass
A33: TC_0032 | B33: TS_002 | C33: FRS | D33: Login | E33: Login with empty Password field | F33: User is on the Login page. | G33: 1. Enter a valid registered email address. 2. Leave the Password field empty. 3. Click the Login button. | H33: Email: testuser@example.com | Password: (empty) | I33: Login is blocked and a validation message 'Password is required' is displayed. | J33: P0 | K33: Negative - Required Field Validation | L33: Pass
A34: TC_0033 | B34: TS_002 | C34: FRS | D34: Login | E34: Login with both Email and Password fields empty | F34: User is on the Login page. | G34: 1. Leave both Email and Password fields empty. 2. Click the Login button. | H34: Email: (empty) | Password: (empty) | I34: Login is blocked and validation messages are displayed for both required fields. | J34: P0 | K34: Negative - Required Field Validation | L34: Pass
A35: TC_0034 | B35: TS_002 | C35: FRS | D35: Login | E35: Login with an invalid email format | F35: User is on the Login page. | G35: 1. Enter an email address in an invalid format. 2. Enter any password. 3. Click the Login button. | H35: Email: testuserexample.com | Password: ValidPassword123! | I35: Login is blocked and a validation message 'Please enter a valid email address' is displayed. | J35: P0 | K35: Negative - Field Format Validation | L35: Pass
A36: TC_0035 | B36: TS_002 | C36: FRS | D36: Login | E36: Login with email in different letter casing than registered | F36: User has a registered account with email 'TestUser@example.com'. | G36: 1. Enter the registered email using different casing (e.g., all lowercase). 2. Enter the correct password. 3. Click the Login button. | H36: Email: testuser@example.com | Password: ValidPassword123! | I36: The user is successfully authenticated, confirming email comparison is case-insensitive. | J36: P0 | K36: Equivalence Partitioning | L36: Pass
A37: TC_0036 | B37: TS_002 | C37: FRS | D37: Login | E37: Login with SQL injection payload in the Email field | F37: User is on the Login page. | G37: 1. Enter a SQL injection payload in the Email field. 2. Enter any value in the Password field. 3. Click the Login button. | H37: Email: admin' OR '1'='1 | Password: anything | I37: Login is rejected with a generic invalid credentials message; no database error is exposed and no unauthorized access is granted. | J37: P0 | K37: Security Testing | L37: Pass
A38: TC_0037 | B38: TS_002 | C38: FRS | D38: Login | E38: Login with 'Remember Me' checkbox checked | F38: User has a registered account and the Login page displays a 'Remember Me' checkbox. | G38: 1. Enter valid credentials. 2. Check the 'Remember Me' checkbox. 3. Click the Login button. 4. Close and reopen the browser, then revisit the site. | H38: Email: testuser@example.com | Password: ValidPassword123! | Remember Me: checked | I38: The user remains logged in after closing and reopening the browser, without needing to log in again. | J38: P0 | K38: Functional Testing | L38: Pass
A39: TC_0038 | B39: TS_002 | C39: FRS | D39: Login | E39: Login with 'Remember Me' checkbox unchecked | F39: User has a registered account. | G39: 1. Enter valid credentials. 2. Leave the 'Remember Me' checkbox unchecked. 3. Click the Login button. 4. Close and reopen the browser, then revisit the site. | H39: Email: testuser@example.com | Password: ValidPassword123! | Remember Me: unchecked | I39: The user's session is not persisted; the user is required to log in again after reopening the browser. | J39: P0 | K39: Functional Testing | L39: Pass
A40: TC_0039 | B40: TS_002 | C40: FRS | D40: Login | E40: Verify Password field masks entered characters on Login page | F40: User is on the Login page. | G40: 1. Click into the Password field. 2. Type a password. 3. Observe the displayed characters. | H40: Password: ValidPassword123! | I40: Entered characters are masked by default (shown as dots/asterisks). | J40: P0 | K40: UI Testing | L40: Pass
A41: TC_0040 | B41: TS_002 | C41: FRS | D41: Login | E41: Verify show/hide password toggle on Login page | F41: User is on the Login page and has entered a password. | G41: 1. Enter a password in the Password field. 2. Click the 'show password' (eye) icon. 3. Observe the field. 4. Click the icon again to hide the password. | H41: Password: ValidPassword123! | I41: Clicking the icon toggles the password visibility between masked and plain text correctly. | J41: P0 | K41: UI Testing | L41: Pass
A42: TC_0041 | B42: TS_002 | C42: FRS | D42: Login | E42: Verify account lockout after multiple consecutive failed login attempts | F42: User has a registered account. Lockout threshold is 5 failed attempts. | G42: 1. Attempt to log in with an incorrect password 5 times in a row. 2. Attempt a 6th login, even with the correct password. | H42: Email: testuser@example.com | Password: wrong (x5), then correct on 6th try | I42: After the 5th failed attempt the account is temporarily locked, and a message such as 'Account temporarily locked, please try again later' is displayed on the 6th attempt. | J42: P0 | K42: Security Testing | L42: Fail
A43: TC_0042 | B43: TS_002 | C43: FRS | D43: Login | E43: Verify failed login attempt counter resets after a successful login | F43: User has 2 prior failed login attempts recorded, below the lockout threshold. | G43: 1. Enter valid credentials. 2. Click the Login button to log in successfully. 3. Log out. 4. Attempt to log in with an incorrect password once more. | H43: Email: testuser@example.com | Password: correct then one wrong attempt | I43: The failed attempt counter resets to zero after a successful login, and the single subsequent failed attempt does not trigger a lockout. | J43: P0 | K43: Business Rule Validation | L43: Pass | M43: Account was not locked after 5 failed attempts; 6th attempt with wrong password was still accepted as a retry without lockout message. | N43: BUG_002 | O43: Ali Hassan | P43: 2026-09-16
A44: TC_0043 | B44: TS_002 | C44: FRS | D44: Login | E44: Verify session expires after a period of user inactivity | F44: User is logged in and the configured session timeout is a fixed inactivity period. | G44: 1. Log in successfully. 2. Remain inactive on the site for longer than the configured session timeout. 3. Attempt to perform an action requiring authentication (e.g., open My Account). | H44: Inactivity period exceeding the configured timeout | I44: The session has expired and the user is redirected to the Login page with a message indicating the session has timed out. | J44: P0 | K44: Session Management | L44: Pass
A45: TC_0044 | B45: TS_002 | C45: FRS | D45: Login | E45: Verify user is redirected to the homepage after successful login | F45: User has a registered account and navigates directly to the Login page. | G45: 1. Navigate directly to the Login page. 2. Enter valid credentials. 3. Click the Login button. | H45: Email: testuser@example.com | Password: ValidPassword123! | I45: The user is redirected to the homepage after successful authentication. | J45: P0 | K45: Navigation Testing | L45: Pass
A46: TC_0045 | B46: TS_002 | C46: FRS | D46: Login | E46: Verify user is redirected back to the originally requested page after login | F46: User attempts to access a restricted page (e.g., Checkout) while logged out. | G46: 1. Attempt to navigate directly to the Checkout page while logged out. 2. The application redirects to the Login page. 3. Enter valid credentials and click Login. | H46: Email: testuser@example.com | Password: ValidPassword123! | I46: After successful login, the user is redirected to the originally requested Checkout page instead of the homepage. | J46: P0 | K46: Navigation Testing | L46: Pass
A47: TC_0046 | B47: TS_002 | C47: FRS | D47: Login | E47: Login with leading and trailing spaces in the Email field | F47: User has a registered account. | G47: 1. Enter the registered email address with leading and trailing spaces. 2. Enter the correct password. 3. Click the Login button. | H47: Email: ' testuser@example.com ' | Password: ValidPassword123! | I47: The application trims the spaces and successfully authenticates the user. | J47: P0 | K47: Equivalence Partitioning | L47: Pass
A48: TC_0047 | B48: TS_002 | C48: FRS | D48: Login | E48: Login with a password containing valid special characters | F48: User has a registered account whose password contains special characters. | G48: 1. Enter the registered email address. 2. Enter the correct password containing special characters. 3. Click the Login button. | H48: Email: testuser@example.com | Password: P@ssw0rd#2024! | I48: The user is successfully authenticated. | J48: P0 | K48: Equivalence Partitioning | L48: Pass
A49: TC_0048 | B49: TS_002 | C49: FRS | D49: Login | E49: Verify navigation to Forgot Password page from Login page | F49: User is on the Login page. | G49: 1. Locate the 'Forgot Password?' link. 2. Click the link. | H49: N/A | I49: The user is navigated to the Forgot Password page successfully. | J49: P0 | K49: Navigation Testing | L49: Pass
A50: TC_0049 | B50: TS_002 | C50: FRS | D50: Login | E50: Verify login session is shared correctly across multiple browser tabs | F50: User is logged in on one browser tab. | G50: 1. Log in successfully in Tab 1. 2. Open a new tab (Tab 2) and navigate to the same site. 3. Check the account/login status in Tab 2. | H50: N/A | I50: The user appears logged in on Tab 2 as well, without needing to log in again. | J50: P0 | K50: Session Management | L50: Pass
A51: TC_0050 | B51: TS_002 | C51: FRS | D51: Login | E51: Verify an already logged-in user cannot access the Login page directly | F51: User is currently logged in. | G51: 1. While logged in, manually navigate to the Login page URL. | H51: N/A | I51: The user is automatically redirected to the homepage or account dashboard instead of seeing the Login form again. | J51: P0 | K51: Business Rule Validation | L51: Pass
A52: TC_0051 | B52: TS_003 | C52: FRS | D52: Logout | E52: Logout from an active user session | F52: User is logged in with an active session. | G52: 1. Click on the user account/profile menu. 2. Click the Logout option. | H52: N/A | I52: The user is logged out successfully and the session is terminated. | J52: P0 | K52: Positive | L52: Pass | M52: Logout terminated session; redirected to homepage. | O52: Youssef Adel | P52: 2026-09-16
A53: TC_0052 | B53: TS_003 | C53: FRS | D53: Logout | E53: Verify Logout option is visible only when a user is logged in | F53: User is not logged in (guest state). | G53: 1. Navigate to the site as a guest. 2. Open the account/profile menu. | H53: N/A | I53: The Logout option is not displayed for guest users; only Login/Register options are visible. | J53: P0 | K53: UI Testing | L53: Pass
A54: TC_0053 | B54: TS_003 | C54: FRS | D54: Logout | E54: Verify user is redirected to the homepage/login page after logout | F54: User is logged in. | G54: 1. Click the Logout option. 2. Observe the page the user lands on. | H54: N/A | I54: The user is redirected to the homepage or login page immediately after logging out. | J54: P0 | K54: Navigation Testing | L54: Pass
A55: TC_0054 | B55: TS_003 | C55: FRS | D55: Logout | E55: Verify the session is fully terminated after logout | F55: User is logged in. | G55: 1. Click Logout. 2. Attempt to access a restricted page (e.g., My Account) via direct URL. | H55: N/A | I55: The user is redirected to the Login page since the session token is no longer valid. | J55: P0 | K55: Security Testing | L55: Pass
A56: TC_0055 | B56: TS_003 | C56: FRS | D56: Logout | E56: Verify using the browser Back button after logout does not restore the session | F56: User has just logged out. | G56: 1. Log out of the application. 2. Click the browser's Back button. 3. Observe the resulting page and account state. | H56: N/A | I56: The previous authenticated page is not restored from cache; the user remains logged out and is prompted to log in if trying to access restricted content. | J56: P0 | K56: Security Testing | L56: Pass
A57: TC_0056 | B57: TS_003 | C57: FRS | D57: Logout | E57: Verify cart items persist correctly after logout for a logged-in user's account | F57: User is logged in and has added items to the cart. | G57: 1. Add one or more products to the cart while logged in. 2. Click Logout. 3. Log back in with the same account. | H57: Cart contains 2 items before logout | I57: The cart items associated with the account are retained and reappear after the user logs back in. | J57: P0 | K57: Business Rule Validation | L57: Pass
A58: TC_0057 | B58: TS_003 | C58: FRS | D58: Logout | E58: Verify logging out from one browser tab terminates the session in all open tabs | F58: User is logged in and has the site open in two browser tabs. | G58: 1. Log in and open the site in two tabs. 2. In Tab 1, click Logout. 3. Switch to Tab 2 and refresh or perform an authenticated action. | H58: N/A | I58: Tab 2 also reflects the logged-out state and redirects to the Login page when an authenticated action is attempted. | J58: P0 | K58: Session Management | L58: Pass
A59: TC_0058 | B59: TS_003 | C59: FRS | D59: Logout | E59: Verify a confirmation or success indicator is shown after logout | F59: User is logged in. | G59: 1. Click the Logout option. 2. Observe the resulting page/notification. | H59: N/A | I59: A clear indication (message, banner, or visible Login/Register option) confirms the user has been logged out successfully. | J59: P0 | K59: UI Testing | L59: Blocked | M59: Unable to test — staging mail server is down, reset emails are not being delivered. | O59: Ali Hassan | P59: 2026-09-17
A60: TC_0059 | B60: TS_003 | C60: FRS | D60: Logout | E60: Attempt to trigger logout with an already-expired or invalid session token | F60: User's session token has already expired due to inactivity. | G60: 1. Wait until the session naturally expires (or simulate an expired token). 2. Click the Logout option. | H60: Expired session token | I60: The application handles the request gracefully, redirecting to the Login page without displaying a technical error. | J60: P0 | K60: Negative - Error Handling | L60: Pass
A61: TC_0060 | B61: TS_003 | C61: FRS | D61: Logout | E61: Verify automatic logout occurs after the configured session timeout period | F61: User is logged in and remains inactive beyond the configured timeout. | G61: 1. Log in successfully. 2. Leave the browser idle for longer than the session timeout duration. 3. Attempt to perform an action requiring authentication. | H61: Idle time exceeding configured timeout | I61: The user is automatically logged out and redirected to the Login page with a session-expired notice. | J61: P0 | K61: Session Management | L61: Pass
A62: TC_0061 | B62: TS_003 | C62: FRS | D62: Logout | E62: Verify re-login works correctly immediately after logout using the same credentials | F62: User has just logged out successfully. | G62: 1. Log out of the application. 2. Navigate to the Login page. 3. Enter the same valid credentials used previously. 4. Click Login. | H62: Email: testuser@example.com | Password: ValidPassword123! | I62: The user is able to log back in successfully and is redirected to the homepage/dashboard. | J62: P0 | K62: Regression Testing | L62: Pass
A63: TC_0062 | B63: TS_004 | C63: FRS | D63: Forgot Password | E63: Request password reset with a valid registered email | F63: User has a registered account and is on the Forgot Password page. | G63: 1. Navigate to the Forgot Password page. 2. Enter a valid registered email address. 3. Click the Submit/Send Reset Link button. | H63: Email: testuser@example.com | I63: A success message is displayed indicating that a password reset link has been sent to the provided email address. | J63: P2 | K63: Positive | L63: Not Run
A64: TC_0063 | B64: TS_004 | C64: FRS | D64: Forgot Password | E64: Request password reset with an unregistered email | F64: The email address entered is not associated with any account. | G64: 1. Navigate to the Forgot Password page. 2. Enter an email address that is not registered. 3. Click the Submit button. | H64: Email: notregistered@example.com | I64: A generic message is displayed ('If an account exists with this email, a reset link has been sent') without confirming whether the account exists. | J64: P2 | K64: Negative - Security Best Practice | L64: Not Run
A65: TC_0064 | B65: TS_004 | C65: FRS | D65: Forgot Password | E65: Request password reset with an empty Email field | F65: User is on the Forgot Password page. | G65: 1. Leave the Email field empty. 2. Click the Submit button. | H65: Email: (empty) | I65: The request is blocked and a validation message 'Email is required' is displayed. | J65: P2 | K65: Negative - Required Field Validation | L65: Not Run
A66: TC_0065 | B66: TS_004 | C66: FRS | D66: Forgot Password | E66: Request password reset with an invalid email format | F66: User is on the Forgot Password page. | G66: 1. Enter an email address in an invalid format. 2. Click the Submit button. | H66: Email: testuserexample | I66: The request is blocked and a validation message 'Please enter a valid email address' is displayed. | J66: P2 | K66: Negative - Field Format Validation | L66: Not Run
A67: TC_0066 | B67: TS_004 | C67: FRS | D67: Forgot Password | E67: Verify the password reset email is received within a reasonable time | F67: User has requested a password reset with a valid registered email. | G67: 1. Submit a password reset request with a valid registered email. 2. Check the associated mailbox inbox (and spam folder). 3. Note the time taken for the email to arrive. | H67: Email: testuser@example.com | I67: The password reset email arrives in the inbox within an acceptable time frame (e.g., under 2 minutes). | J67: P2 | K67: Functional Testing | L67: Not Run
A68: TC_0067 | B68: TS_004 | C68: FRS | D68: Forgot Password | E68: Verify the content and formatting of the password reset email | F68: A password reset email has been received. | G68: 1. Open the received password reset email. 2. Review the sender address, subject line, body text, and reset link/button. | H68: N/A | I68: The email displays a professional, correctly formatted message with a clear call-to-action button/link and no broken content. | J68: P2 | K68: UI Testing | L68: Not Run
A69: TC_0068 | B69: TS_004 | C69: FRS | D69: Forgot Password | E69: Verify clicking the reset link navigates to the Reset Password page | F69: A valid password reset email has been received. | G69: 1. Open the password reset email. 2. Click the reset password link/button. | H69: N/A | I69: The user is navigated to the Reset Password page where a new password can be entered. | J69: P2 | K69: Navigation Testing | L69: Not Run
A70: TC_0069 | B70: TS_004 | C70: FRS | D70: Forgot Password | E70: Reset password with a valid new password | F70: User has clicked a valid, unexpired password reset link. | G70: 1. On the Reset Password page, enter a new password meeting complexity rules. 2. Re-enter the same password in the Confirm Password field. 3. Click the Reset Password/Submit button. | H70: New Password: NewPass!456 | Confirm: NewPass!456 | I70: The password is reset successfully and a confirmation message is displayed, prompting the user to log in with the new password. | J70: P2 | K70: Positive | L70: Not Run
A71: TC_0070 | B71: TS_004 | C71: FRS | D71: Forgot Password | E71: Reset password using the same value as the current password | F71: User has clicked a valid password reset link. Current password is known. | G71: 1. On the Reset Password page, enter the same password as the current/old one. 2. Confirm the same password. 3. Click Submit. | H71: New Password: OldPassword123! (same as current) | I71: The application blocks the request and displays a message such as 'New password must be different from the current password'. | J71: P2 | K71: Business Rule Validation | L71: Not Run
... A76: TC_0075 | B76: TS_004 | C76: FRS | D76: Forgot Password | E76: Attempt to reuse an already-used password reset link | F76: A password reset link has already been successfully used once. | G76: 1. Complete a password reset using a valid link. 2. Click the same reset link again. 3. Attempt to set another new password. | H76: Previously used reset link/token | I76: The application rejects the request with a message such as 'This link is no longer valid' since the token has already been consumed. | J76: P2 | K76: Security Testing | L76: Not Run
A77: TC_0076 | B77: TS_004 | C77: FRS | D77: Forgot Password | E77: Attempt to access the Reset Password page with an invalid or tampered token | F77: No valid reset request has been made, or the token has been manually altered. | G77: 1. Manually modify a portion of the reset link/token in the URL. 2. Navigate to the modified URL. | H77: Tampered token string | I77: The application rejects the invalid token and displays an appropriate error message without exposing sensitive details. | J77: P2 | K77: Security Testing | L77: Pass | M77: New password accepted and login with new password succeeded. | O77: Ali Hassan | P77: 2026-09-17
A78: TC_0077 | B78: TS_004 | C78: FRS | D78: Forgot Password | E78: Verify the password reset link expiration time is enforced correctly | F78: The system configuration specifies a fixed expiration window for reset links (e.g., 24 hours). | G78: 1. Generate a password reset link. 2. Wait until just after the expiration window elapses. 3. Attempt to use the link. | H78: Reset link older than the configured expiration window | I78: The link is correctly identified as expired and the user is prompted to request a new reset email. | J78: P2 | K78: Business Rule Validation | L78: Not Run
A79: TC_0078 | B79: TS_004 | C79: FRS | D79: Forgot Password | E79: Verify successful login using the newly reset password | F79: The user has just completed a password reset successfully. | G79: 1. Navigate to the Login page. 2. Enter the registered email address. 3. Enter the newly set password. 4. Click Login. | H79: Email: testuser@example.com | Password: NewPass!456 | I79: The user is authenticated successfully using the new password and redirected to the homepage/dashboard. | J79: P2 | K79: Regression Testing | L79: Not Run
A80: TC_0079 | B80: TS_004 | C80: FRS | D80: Forgot Password | E80: Verify the old password is rejected after a successful password reset | F80: The user has just completed a password reset successfully. | G80: 1. Navigate to the Login page. 2. Enter the registered email address. 3. Enter the old (previous) password. 4. Click Login. | H80: Email: testuser@example.com | Password: OldPassword123! | I80: Login is rejected with an 'Invalid email or password' message, confirming the old password is no longer valid. | J80: P2 | K80: Security Testing | L80: Not Run
A81: TC_0080 | B81: TS_004 | C81: FRS | D81: Forgot Password | E81: Verify rate limiting when requesting multiple reset emails in quick succession | F81: User has a registered account and is on the Forgot Password page. | G81: 1. Submit a password reset request. 2. Immediately submit the same request 4-5 more times in quick succession. | H81: Email: testuser@example.com submitted repeatedly | I81: After a defined threshold, the application throttles further requests and displays a message such as 'Please wait before requesting another reset email'. | J81: P2 | K81: Security Testing | L81: Not Run
A82: TC_0081 | B82: TS_004 | C82: FRS | D82: Forgot Password | E82: Verify the 'Forgot Password' link is accessible from the Login page | F82: User is on the Login page. | G82: 1. Locate the 'Forgot Password?' link on the Login page. 2. Click the link. | H82: N/A | I82: The user is navigated to the Forgot Password page. | J82: P2 | K82: Navigation Testing | L82: Not Run
A83: TC_0082 | B83: TS_004 | C83: FRS | D83: Forgot Password | E83: Verify Cancel/Back navigation from the Forgot Password page | F83: User is on the Forgot Password page. | G83: 1. Click the Cancel/Back link or browser back navigation. 2. Observe the resulting page. | H83: N/A | I83: The user is returned to the Login page (or previous page) without submitting a reset request. | J83: P2 | K83: Navigation Testing | L83: Not Run
A84: TC_0083 | B84: TS_004 | C84: FRS | D84: Forgot Password | E84: Verify the new password field masks entered characters on the Reset Password page | F84: User has navigated to the Reset Password page via a valid link. | G84: 1. Click into the New Password field. 2. Type a new password. 3. Observe the displayed characters. | H84: New Password: NewPass!456 | I84: Entered characters are masked by default (shown as dots/asterisks). | J84: P2 | K84: UI Testing | L84: Not Run
A85: TC_0084 | B85: TS_004 | C85: FRS | D85: Forgot Password | E85: Verify a success message is displayed after submitting a valid reset request | F85: User is on the Forgot Password page. | G85: 1. Enter a valid registered email. 2. Click Submit. | H85: Email: testuser@example.com | I85: A clear, user-friendly success message confirming the email has been sent is displayed on screen. | J85: P2 | K85: UI Testing | L85: Pass | M85: Exact keyword search returned the correct product at top of results. | O85: Mona Fathy | P85: 2026-09-17
A86: TC_0085 | B86: TS_004 | C86: FRS | D86: Forgot Password | E86: Request password reset with an email containing leading/trailing spaces | F86: User has a registered account. | G86: 1. Enter the registered email address with leading and trailing spaces. 2. Click Submit. | H86: Email: ' testuser@example.com ' | I86: The application trims the spaces and processes the request successfully, sending the reset email. | J86: P2 | K86: Equivalence Partitioning | L86: Not Run
A87: TC_0086 | B87: TS_004 | C87: FRS | D87: Forgot Password | E87: Verify the reset request response does not reveal whether an email exists in the system | F87: User is on the Forgot Password page. | G87: 1. Submit a reset request using a registered email and note the response message. 2. Submit a reset request using an unregistered email and compare the response message. | H87: Registered vs. unregistered email addresses | I87: Both requests return the same generic confirmation message, preventing user enumeration attacks. | J87: P2 | K87: Security Testing | L87: Not Run
A88: TC_0087 | B88: TS_005 | C88: FRS | D88: Search | E88: Search using the exact product name | F88: Products exist in the catalog, e.g., 'Wireless Bluetooth Headphones'. | G88: 1. Click on the Search bar. 2. Type the exact product name. 3. Press Enter or click the Search icon. | H88: Search term: Wireless Bluetooth Headphones | I88: The exact matching product is displayed at the top of the search results. | J88: P1 | K88: Positive | L88: Not Run
A89: TC_0088 | B89: TS_005 | C89: FRS | D89: Search | E89: Search using a partial keyword | F89: Products containing the keyword exist in the catalog. | G89: 1. Click on the Search bar. 2. Type a partial keyword from a product name. 3. Press Enter. | H89: Search term: 'headphone' | I89: All products whose name or description contains the keyword are displayed in the results. | J89: P1 | K89: Positive | L89: Not Run
A90: TC_0089 | B90: TS_005 | C90: FRS | D90: Search | E90: Search with a keyword that has no matching products | F90: No product in the catalog matches the search term. | G90: 1. Click on the Search bar. 2. Type a keyword that does not exist in the catalog. 3. Press Enter. | H90: Search term: 'xyzxyznotaproduct' | I90: A 'No results found' message is displayed along with helpful suggestions or related categories. | J90: P1 | K90: Negative - Equivalence Partitioning | L90: Not Run
A91: TC_0090 | B91: TS_005 | C91: FRS | D91: Search | E91: Search with an empty search field | F91: User is on any page with the search bar visible. | G91: 1. Click on the Search bar without typing anything. 2. Press Enter or click the Search icon. | H91: Search term: (empty) | I91: The search is not executed, or the page displays a prompt asking the user to enter a search term; no error/crash occurs. | J91: P1 | K91: Negative - Required Field Validation | L91: Pass | M91: No-match search showed 'No results found' with suggestions. | O91: Ali Hassan | P91: 2026-09-17
A92: TC_0091 | B92: TS_005 | C92: FRS | D92: Search | E92: Search using special characters only | F92: User is on a page with the search bar. | G92: 1. Click on the Search bar. 2. Type only special characters. 3. Press Enter. | H92: Search term: '@#$%^&*' | I92: No results are found and a friendly 'No results found' message is displayed without any application error. | J92: P1 | K92: Negative - Field Validation | L92: Not Run
A93: TC_0092 | B93: TS_005 | C93: FRS | D93: Search | E93: Search with a SQL injection payload | F93: User is on a page with the search bar. | G93: 1. Click on the Search bar. 2. Type a SQL injection payload. 3. Press Enter. | H93: Search term: ' OR '1'='1 | I93: The input is safely handled as plain text with no results found or a validation message; no database error or data exposure occurs. | J93: P1 | K93: Security Testing | L93: Not Run
A94: TC_0093 | B94: TS_005 | C94: FRS | D94: Search | E94: Search using different letter casing (case-insensitivity check) | F94: A product named 'Running Shoes' exists in the catalog. | G94: 1. Click on the Search bar. 2. Type the product name in a different case, e.g., all uppercase. 3. Press Enter. | H94: Search term: 'RUNNING SHOES' | I94: The search returns the same results as searching with the original casing, confirming case-insensitive matching. | J94: P1 | K94: Equivalence Partitioning | L94: Not Run
A95: TC_0094 | B95: TS_005 | C95: FRS | D95: Search | E95: Search with leading and trailing spaces in the search term | F95: A product matching the keyword exists in the catalog. | G95: 1. Click on the Search bar. 2. Type a valid keyword with leading and trailing spaces. 3. Press Enter. | H95: Search term: ' shoes ' | I95: The application trims the spaces and returns the same relevant results as a trimmed search. | J95: P1 | K95: Equivalence Partitioning | L95: Not Run
A96: TC_0095 | B96: TS_005 | C96: FRS | D96: Search | E96: Search with a single character (minimum boundary input) | F96: User is on a page with the search bar. | G96: 1. Click on the Search bar. 2. Type a single character. 3. Press Enter. | H96: Search term: 's' | I96: The application either returns broad matching results or displays a message requesting a more specific search term (based on defined minimum length rule). | J96: P1 | K96: Boundary Value Analysis | L96: Not Run
A97: TC_0096 | B97: TS_005 | C97: FRS | D97: Search | E97: Search with the maximum allowed number of characters | F97: The search field has a defined maximum character limit (e.g., 100 characters). | G97: 1. Click on the Search bar. 2. Type a search term with exactly the maximum allowed characters. 3. Press Enter. | H97: Search term: 100-character string | I97: The search executes successfully without truncation errors or crashes. | J97: P1 | K97: Boundary Value Analysis | L97: Not Run
A98: TC_0097 | B98: TS_005 | C98: FRS | D98: Search | E98: Search exceeding the maximum allowed number of characters | F98: The search field has a defined maximum character limit (e.g., 100 characters). | G98: 1. Click on the Search bar. 2. Type a search term exceeding the maximum allowed characters. 3. Press Enter. | H98: Search term: 101+ character string | I98: The input is either truncated at the limit or a validation message is displayed; no application error occurs. | J98: P1 | K98: Boundary Value Analysis | L98: Not Run
A99: TC_0098 | B99: TS_005 | C99: FRS | D99: Search | E99: Search using a numeric product SKU/code | F99: A product with a known SKU code exists in the catalog. | G99: 1. Click on the Search bar. 2. Type the exact numeric SKU code of a product. 3. Press Enter. | H99: Search term: 'SKU-102345' | I99: The product matching the SKU code is displayed in the search results. | J99: P1 | K99: Positive | L99: Not Run
A100: TC_0099 | B100: TS_005 | C100: FRS | D100: Search | E100: Search with a misspelled keyword to verify search suggestions | F100: A product named 'Bluetooth Speaker' exists in the catalog. | G100: 1. Click on the Search bar. 2. Type a slightly misspelled version of the product name. 3. Press Enter. | H100: Search term: 'Blutooth Speeker' | I100: The application displays 'Did you mean...' suggestions or still returns relevant fuzzy-matched results. | J100: P1 | K100: Usability Testing | L100: Not Run
A101: TC_0100 | B101: TS_005 | C101: FRS | D101: Search | E101: Verify autocomplete suggestions appear while typing in the search bar | F101: The catalog contains products related to common keywords. | G101: 1. Click on the Search bar. 2. Begin typing a partial keyword, pausing after a few characters. 3. Observe the suggestion dropdown. | H101: Search term (partial): 'lap' | I101: A dropdown list of relevant autocomplete suggestions (e.g., 'Laptop', 'Laptop Bag') appears in real time as the user types. | J101: P1 | K101: UI Testing | L101: Fail | M101: Search with SQL injection payload returned a 500 server error instead of an empty result set. | N101: BUG_003 | O101: Mona Fathy | P101: 2026-09-17
A102: TC_0101 | B102: TS_005 | C102: FRS | D102: Search | E102: Verify search results can be filtered by category | F102: Search results contain products from multiple categories. | G102: 1. Perform a broad search returning multiple categories of products. 2. Apply a category filter (e.g., 'Electronics') from the sidebar. 3. Observe the updated results. | H102: Search term: 'phone' | Filter: Electronics | I102: Only products belonging to the selected category are displayed in the filtered results. | J102: P1 | K102: Functional Testing | L102: Not Run
A103: TC_0102 | B103: TS_005 | C103: FRS | D103: Search | E103: Verify search results can be filtered by price range | F103: Search results contain products across a range of prices. | G103: 1. Perform a search returning multiple products. 2. Apply a price range filter (e.g., $50-$100). 3. Observe the updated results. | H103: Search term: 'shoes' | Price filter: $50-$100 | I103: Only products within the specified price range are displayed. | J103: P1 | K103: Functional Testing | L103: Not Run
A104: TC_0103 | B104: TS_005 | C104: FRS | D104: Search | E104: Verify search results can be sorted by price from low to high | F104: Search results contain multiple products at different prices. | G104: 1. Perform a search returning multiple products. 2. Select the 'Price: Low to High' sort option. 3. Observe the order of results. | H104: Search term: 'shoes' | Sort: Price Low-High | I104: Products are displayed in ascending order of price. | J104: P1 | K104: Functional Testing | L104: Not Run
...

Sheet Test Cases (Simple)
A1: Test Case ID | B1: Test Case Title | C1: Test Steps | D1: Test Data | E1: Expected Result
A2: TC_0001 | B2: Register with valid mandatory data | C2: 1. Navigate to the Registration page. 2. Enter a valid first name, last name, and a unique email address. 3. Enter a password that meets complexity rules. 4. Re-enter the same password in the Confirm Password field. 5. Check the 'I agree to Terms and Conditions' checkbox. 6. Click the Register button. | D2: First Name: Sarah | Last Name: Ahmed | Email: sarah.ahmed01@example.com | Password: Passw0rd!23 | E2: Account is created successfully, a confirmation message is shown, and the user is redirected to the login page or homepage as a logged-in user.
A3: TC_0002 | B3: Register with empty First Name field | C3: 1. Leave the First Name field empty. 2. Fill in all other required fields with valid data. 3. Click the Register button. | D3: First Name: (empty) | Last Name: Hassan | Email: hassan.t@example.com | Password: Passw0rd!23 | E3: Registration is blocked and an inline validation message 'First name is required' is displayed under the First Name field.
A4: TC_0003 | B4: Register with empty Last Name field | C4: 1. Leave the Last Name field empty. 2. Fill in all other required fields with valid data. 3. Click the Register button. | D4: First Name: Omar | Last Name: (empty) | Email: omar.k@example.com | Password: Passw0rd!23 | E4: Registration is blocked and an inline validation message 'Last name is required' is displayed under the Last Name field.
A5: TC_0004 | B5: Register with empty Email field | C5: 1. Leave the Email field empty. 2. Fill in all other required fields with valid data. 3. Click the Register button. | D5: Email: (empty) | E5: Registration is blocked and an inline validation message 'Email is required' is displayed under the Email field.
A6: TC_0005 | B6: Register with empty Password field | C6: 1. Leave the Password field empty. 2. Fill in all other required fields with valid data. 3. Click the Register button. | D6: Password: (empty) | E6: Registration is blocked and an inline validation message 'Password is required' is displayed under the Password field.
A7: TC_0006 | B7: Register with empty Confirm Password field | C7: 1. Enter a valid password in the Password field. 2. Leave the Confirm Password field empty. 3. Click the Register button. | D7: Password: Passw0rd!23 | Confirm Password: (empty) | E7: Registration is blocked and a validation message 'Please confirm your password' is displayed.
A8: TC_0007 | B8: Register with invalid email format - missing @ symbol | C8: 1. Fill in all fields with valid data. 2. Enter an email address without an '@' symbol. 3. Click the Register button. | D8: Email: sarahexample.com | E8: Registration is blocked and a validation message 'Please enter a valid email address' is displayed.
A9: TC_0008 | B9: Register with invalid email format - missing domain | C9: 1. Fill in all fields with valid data. 2. Enter an email address without a domain after the '@' symbol. 3. Click the Register button. | D9: Email: sarah.ahmed@ | E9: Registration is blocked and a validation message 'Please enter a valid email address' is displayed.
A10: TC_0009 | B10: Register with an already registered email address | C10: 1. Navigate to the Registration page. 2. Fill in the form using an email address that is already registered. 3. Click the Register button. | D10: Email: existing.user@example.com | E10: Registration is blocked and an error message 'An account with this email already exists' is displayed, with a suggestion to log in instead.
A11: TC_0010 | B11: Register with password shorter than minimum allowed length | C11: 1. Fill in all fields with valid data. 2. Enter a password with 7 characters. 3. Click the Register button. | D11: Password: Pas1!aB (7 characters) | E11: Registration is blocked and a validation message 'Password must be at least 8 characters long' is displayed.
A12: TC_0011 | B12: Register with password at exact minimum allowed length | C12: 1. Fill in all fields with valid data. 2. Enter a password with exactly 8 characters meeting complexity rules. 3. Click the Register button. | D12: Password: Pass1!aB (8 characters) | E12: Password is accepted and the account is registered successfully.
... A272: TC_0271 | B272: Logout successfully from the My Account page | C272: 1. Navigate to the My Account page. 2. Click the Logout option from the account menu. | D272: N/A | E272: The user is logged out successfully and redirected to the homepage or login page, with the session terminated.

Sheet Test Execution
A1: Test Case ID | B1: Test Scenario ID | C1: Module | D1: Priority | E1: Status | F1: Executed By | G1: Execution Date | H1: Defect ID | I1: Comments
A2: ='Test Cases'!A2 -> TC_0001 | B2: ='Test Cases'!B2 -> TS_001 | C2: ='Test Cases'!D2 -> Register | D2: ='Test Cases'!J2 -> P0 | E2: ='Test Cases'!L2 -> Pass | F2: ='Test Cases'!O2 -> Ali Hassan | G2: ='Test Cases'!P2 -> 2026-09-15 | H2: ='Test Cases'!N2 -> 0
A3: ='Test Cases'!A3 -> TC_0002 | B3: ='Test Cases'!B3 -> TS_001 | C3: ='Test Cases'!D3 -> Register | D3: ='Test Cases'!J3 -> P0 | E3: ='Test Cases'!L3 -> Pass | F3: ='Test Cases'!O3 -> Mona Fathy | G3: ='Test Cases'!P3 -> 2026-09-15 | H3: ='Test Cases'!N3 -> 0
A4: ='Test Cases'!A4 -> TC_0003 | B4: ='Test Cases'!B4 -> TS_001 | C4: ='Test Cases'!D4 -> Register | D4: ='Test Cases'!J4 -> P0 | E4: ='Test Cases'!L4 -> Pass | F4: ='Test Cases'!O4 -> 0 | G4: ='Test Cases'!P4 -> 0 | H4: ='Test Cases'!N4 -> 0
A5: ='Test Cases'!A5 -> TC_0004 | B5: ='Test Cases'!B5 -> TS_001 | C5: ='Test Cases'!D5 -> Register | D5: ='Test Cases'!J5 -> P0 | E5: ='Test Cases'!L5 -> Pass | F5: ='Test Cases'!O5 -> 0 | G5: ='Test Cases'!P5 -> 0 | H5: ='Test Cases'!N5 -> 0
A6: ='Test Cases'!A6 -> TC_0005 | B6: ='Test Cases'!B6 -> TS_001 | C6: ='Test Cases'!D6 -> Register | D6: ='Test Cases'!J6 -> P0 | E6: ='Test Cases'!L6 -> Pass | F6: ='Test Cases'!O6 -> 0 | G6: ='Test Cases'!P6 -> 0 | H6: ='Test Cases'!N6 -> 0
A7: ='Test Cases'!A7 -> TC_0006 | B7: ='Test Cases'!B7 -> TS_001 | C7: ='Test Cases'!D7 -> Register | D7: ='Test Cases'!J7 -> P0 | E7: ='Test Cases'!L7 -> Pass | F7: ='Test Cases'!O7 -> 0 | G7: ='Test Cases'!P7 -> 0 | H7: ='Test Cases'!N7 -> 0
A8: ='Test Cases'!A8 -> TC_0007 | B8: ='Test Cases'!B8 -> TS_001 | C8: ='Test Cases'!D8 -> Register | D8: ='Test Cases'!J8 -> P0 | E8: ='Test Cases'!L8 -> Pass | F8: ='Test Cases'!O8 -> 0 | G8: ='Test Cases'!P8 -> 0 | H8: ='Test Cases'!N8 -> 0
A9: ='Test Cases'!A9 -> TC_0008 | B9: ='Test Cases'!B9 -> TS_001 | C9: ='Test Cases'!D9 -> Register | D9: ='Test Cases'!J9 -> P0 | E9: ='Test Cases'!L9 -> Pass | F9: ='Test Cases'!O9 -> 0 | G9: ='Test Cases'!P9 -> 0 | H9: ='Test Cases'!N9 -> 0
A10: ='Test Cases'!A10 -> TC_0009 | B10: ='Test Cases'!B10 -> TS_001 | C10: ='Test Cases'!D10 -> Register | D10: ='Test Cases'!J10 -> P0 | E10: ='Test Cases'!L10 -> Fail | F10: ='Test Cases'!O10 -> Mona Fathy | G10: ='Test Cases'!P10 -> 2026-09-15 | H10: ='Test Cases'!N10 -> BUG_001
A11: ='Test Cases'!A11 -> TC_0010 | B11: ='Test Cases'!B11 -> TS_001 | C11: ='Test Cases'!D11 -> Register | D11: ='Test Cases'!J11 -> P0 | E11: ='Test Cases'!L11 -> Not Run | F11: ='Test Cases'!O11 -> 0 | G11: ='Test Cases'!P11 -> 0 | H11: ='Test Cases'!N11 -> 0
A12: ='Test Cases'!A12 -> TC_0011 | B12: ='Test Cases'!B12 -> TS_001 | C12: ='Test Cases'!D12 -> Register | D12: ='Test Cases'!J12 -> P0 | E12: ='Test Cases'!L12 -> Not Run | F12: ='Test Cases'!O12 -> 0 | G12: ='Test Cases'!P12 -> 0 | H12: ='Test Cases'!N12 -> 0
A13: ='Test Cases'!A13 -> TC_0012 | B13: ='Test Cases'!B13 -> TS_001 | C13: ='Test Cases'!D13 -> Register | D13: ='Test Cases'!J13 -> P0 | E13: ='Test Cases'!L13 -> Not Run | F13: ='Test Cases'!O13 -> 0 | G13: ='Test Cases'!P13 -> 0 | H13: ='Test Cases'!N13 -> 0
... A272: ='Test Cases'!A272 -> TC_0271 | B272: ='Test Cases'!B272 -> TS_013 | C272: ='Test Cases'!D272 -> My Account | D272: ='Test Cases'!J272 -> P2 | E272: ='Test Cases'!L272 -> Not Run | F272: ='Test Cases'!O272 -> 0 | G272: ='Test Cases'!P272 -> 0 | H272: ='Test Cases'!N272 -> 0

Sheet Bug Tracker
A1: Bug ID | B1: Summary | C1: Test Case ID | D1: Module | E1: Severity | F1: Priority | G1: Status | H1: Environment | I1: Steps to Reproduce | J1: Expected Result | K1: Actual Result | L1: Assigned To | M1: Created Date | N1: Closed Date
A2: =IF(B2="","","BUG_"&TEXT(ROW()-1,"000")) -> BUG_001 | B2: Duplicate account created with an already-registered email | C2: TC_0009 | D2: Register | E2: High | F2: P0 | G2: Open | H2: Staging - Chrome 128 | I2: 1. Register a new account using an email that already exists in the system. 2. Submit the registration form. | J2: Registration should be blocked with an 'account already exists' error message. | K2: The account was created successfully with no error, resulting in a duplicate email in the database. | L2: Dev Team - Backend | M2: 2026-09-15
A3: =IF(B3="","","BUG_"&TEXT(ROW()-1,"000")) -> BUG_002 | B3: Account lockout not enforced after repeated failed login attempts | C3: TC_0042 | D3: Login | E3: Critical | F3: P0 | G3: Open | H3: Staging - Chrome 128 | I3: 1. Attempt to log in with an incorrect password 5 times consecutively. 2. Attempt a 6th login. | J3: The account should be temporarily locked after 5 failed attempts, with a lockout message on the 6th attempt. | K3: No lockout occurred; the 6th attempt was processed as a normal login retry. | L3: Dev Team - Backend | M3: 2026-09-16
A4: =IF(B4="","","BUG_"&TEXT(ROW()-1,"000")) -> BUG_003 | B4: Search field vulnerable to SQL injection payload causing server error | C4: TC_0100 | D4: Search | E4: Critical | F4: P1 | G4: New | H4: Staging - Chrome 128 | I4: 1. Enter a SQL injection payload ( ' OR '1'='1 ) into the search bar. 2. Submit the search. | J4: The input should be safely handled as plain text, returning no results without any server error. | K4: The server returned an HTTP 500 error page instead of handling the input safely. | L4: Dev Team - Backend | M4: 2026-09-17
A5: =IF(B5="","","BUG_"&TEXT(ROW()-1,"000")) -> BUG_004 | B5: Expired coupon code incorrectly accepted and discount applied | C5: TC_0225 | D5: Shopping Cart | E5: High | F5: P1 | G5: Open | H5: Staging - Chrome 128 | I5: 1. Add items to the cart. 2. Apply a coupon code that has passed its expiration date. | J5: The expired coupon should be rejected with an 'invalid or expired coupon' message. | K5: The expired coupon was accepted and the discount was applied to the order total. | L5: Dev Team - Backend | M5: 2026-09-19
A6: =IF(B6="","","BUG_"&TEXT(ROW()-1,"000")) -> BUG_005 | B6: Duplicate order created on rapid double-click of Place Order | C6: TC_0258 | D6: Checkout | E6: Critical | F6: P1 | G6: New | H6: Staging - Chrome 128 | I6: 1. Complete all checkout steps with valid data. 2. Rapidly double-click the 'Place Order' button before the page responds. | J6: Only one order should be created; the button should disable after the first click. | K6: Two separate orders were created for a single checkout attempt, resulting in a duplicate charge risk. | L6: Dev Team - Frontend | M6: 2026-09-20
A7: =IF(B7="","","BUG_"&TEXT(ROW()-1,"000"))
A8: =IF(B8="","","BUG_"&TEXT(ROW()-1,"000"))
A9: =IF(B9="","","BUG_"&TEXT(ROW()-1,"000"))
A10: =IF(B10="","","BUG_"&TEXT(ROW()-1,"000"))
A11: =IF(B11="","","BUG_"&TEXT(ROW()-1,"000"))
A12: =IF(B12="","","BUG_"&TEXT(ROW()-1,"000"))
A13: =IF(B13="","","BUG_"&TEXT(ROW()-1,"000"))
A14: =IF(B14="","","BUG_"&TEXT(ROW()-1,"000"))
A15: =IF(B15="","","BUG_"&TEXT(ROW()-1,"000"))
A16: =IF(B16="","","BUG_"&TEXT(ROW()-1,"000"))
A17: =IF(B17="","","BUG_"&TEXT(ROW()-1,"000"))
A18: =IF(B18="","","BUG_"&TEXT(ROW()-1,"000"))
... A61: =IF(B61="","","BUG_"&TEXT(ROW()-1,"000"))

Sheet Requirements
A1: Requirement ID | B1: Reference | C1: Requirement / Feature | D1: Related Test Scenario | E1: Priority
A2: REQ_001 | B2: FRS | C2: The system shall allow a new user to create an account by providing mandatory registration details, validating all inputs, and preventing duplicate accounts. | D2: TS_001 | E2: P0
A3: REQ_002 | B3: FRS | C3: The system shall allow a registered user to securely authenticate using their email and password, including session and lockout handling. | D3: TS_002 | E3: P0
A4: REQ_003 | B4: FRS | C4: The system shall allow an authenticated user to securely terminate their session at any time. | D4: TS_003 | E4: P0
A5: REQ_004 | B5: FRS | C5: The system shall allow a user who forgot their password to securely reset it via a time-limited, single-use email link. | D5: TS_004 | E5: P2
A6: REQ_005 | B6: FRS | C6: The system shall allow users to search the product catalog by keyword, SKU, or partial match, with sorting, filtering, and pagination. | D6: TS_005 | E6: P1
A7: REQ_006 | B7: FRS | C7: The system shall allow users to select multiple products and view a side-by-side comparison of their attributes. | D7: TS_006 | E7: P4
A8: REQ_007 | B8: FRS | C8: The system shall display complete, accurate product information including price, images, variants, stock, and reviews on the Product Display Page. | D8: TS_007 | E8: P1
A9: REQ_008 | B9: FRS | C9: The system shall allow users to add available products to their shopping cart with the desired quantity and variant. | D9: TS_008 | E9: P1
A10: REQ_009 | B10: FRS | C10: The system shall allow logged-in users to save products of interest to a persistent wishlist for later purchase. | D10: TS_009 | E10: P4
A11: REQ_010 | B11: FRS | C11: The system shall allow users to review, modify, and accurately price the contents of their shopping cart prior to checkout. | D11: TS_010 | E11: P1
A12: REQ_011 | B12: FRS | C12: The system shall present an engaging, functional homepage that provides entry points to key site sections and promotions. | D12: TS_011 | E12: P2
... A14: REQ_013 | B14: FRS | C14: The system shall allow authenticated users to view and manage their profile, password, and order history. | D14: TS_013 | E14: P2

Sheet Dashboard
B2: Manual Testing — QA Dashboard
B3: E-Commerce Web Application | Live metrics computed from the 'Test Cases' sheet
B5: Execution Summary
B6: Total Test Cases | C6: Not Run | D6: Pass | E6: Fail | F6: Blocked | G6: Pass Rate | H6: Fail Rate
B7: =COUNTA('Test Cases'!$L$2:$L$272) -> 271 | C7: =COUNTIF('Test Cases'!$L$2:$L$272,"Not Run") -> 196 | D7: =COUNTIF('Test Cases'!$L$2:$L$272,"Pass") -> 69 | E7: =COUNTIF('Test Cases'!$L$2:$L$272,"Fail") -> 5 | F7: =COUNTIF('Test Cases'!$L$2:$L$272,"Blocked") -> 1 | G7: =IFERROR(D7/B7,0) -> 0.25461255 | H7: =IFERROR(E7/B7,0) -> 0.018450185
B10: Test Cases by Priority | E10: Test Cases by Module
B11: Priority | C11: Count | E11: Module | F11: Count
B12: P0 | C12: =COUNTIF('Test Cases'!$J$2:$J$272,"P0") -> 61 | E12: Register | F12: =COUNTIF('Test Cases'!$D$2:$D$272,"Register") -> 27
B13: P1 | C13: =COUNTIF('Test Cases'!$J$2:$J$272,"P1") -> 121 | E13: Login | F13: =COUNTIF('Test Cases'!$D$2:$D$272,"Login") -> 23
B14: P2 | C14: =COUNTIF('Test Cases'!$J$2:$J$272,"P2") -> 44 | E14: Logout | F14: =COUNTIF('Test Cases'!$D$2:$D$272,"Logout") -> 11
B15: P4 | C15: =COUNTIF('Test Cases'!$J$2:$J$272,"P4") -> 45 | E15: Forgot Password | F15: =COUNTIF('Test Cases'!$D$2:$D$272,"Forgot Password") -> 25
E16: Search | F16: =COUNTIF('Test Cases'!$D$2:$D$272,"Search") -> 22
E17: Product Compare | F17: =COUNTIF('Test Cases'!$D$2:$D$272,"Product Compare") -> 24
E18: Product Display Page | F18: =COUNTIF('Test Cases'!$D$2:$D$272,"Product Display Page") -> 37
E19: Add to Cart | F19: =COUNTIF('Test Cases'!$D$2:$D$272,"Add to Cart") -> 9
E20: Wish List | F20: =COUNTIF('Test Cases'!$D$2:$D$272,"Wish List") -> 21
E21: Shopping Cart | F21: =COUNTIF('Test Cases'!$D$2:$D$272,"Shopping Cart") -> 33
E22: Home Page | F22: =COUNTIF('Test Cases'!$D$2:$D$272,"Home Page") -> 10
E23: Checkout | F23: =COUNTIF('Test Cases'!$D$2:$D$272,"Checkout") -> 20
E24: My Account | F24: =COUNTIF('Test Cases'!$D$2:$D$272,"My Account") -> 9
B27: Test Execution Status
B28: Status | C28: Count
B29: Not Run | C29: =COUNTIF('Test Cases'!$L$2:$L$272,"Not Run") -> 196
B30: Pass | C30: =COUNTIF('Test Cases'!$L$2:$L$272,"Pass") -> 69
B31: Fail | C31: =COUNTIF('Test Cases'!$L$2:$L$272,"Fail") -> 5
B32: Blocked | C32: =COUNTIF('Test Cases'!$L$2:$L$272,"Blocked") -> 1
B33: N/A | C33: =COUNTIF('Test Cases'!$L$2:$L$272,"N/A") -> 0
B36: Charts
